mindzie_api/__init__.py
mindzie_api/__version__.py
mindzie_api/auth.py
mindzie_api/client.py
mindzie_api/constants.py
mindzie_api/exceptions.py
mindzie_api/utils.py
mindzie_api/controllers/__init__.py
mindzie_api/controllers/action.py
mindzie_api/controllers/actionexecution.py
mindzie_api/controllers/block.py
mindzie_api/controllers/copilot.py
mindzie_api/controllers/dashboard.py
mindzie_api/controllers/dataset.py
mindzie_api/controllers/enrichment.py
mindzie_api/controllers/execution.py
mindzie_api/controllers/investigation.py
mindzie_api/controllers/notebook.py
mindzie_api/controllers/ping.py
mindzie_api/controllers/project.py
mindzie_api/controllers/tenant.py
mindzie_api/controllers/user.py
mindzie_api/models/__init__.py
mindzie_api/models/base.py
mindzie_api/models/block.py
mindzie_api/models/copilot.py
mindzie_api/models/dashboard.py
mindzie_api/models/dataset.py
mindzie_api/models/enrichment.py
mindzie_api/models/execution.py
mindzie_api/models/investigation.py
mindzie_api/models/notebook.py
mindzie_api/models/project.py
mindzie_api/models/tenant.py
mindzie_api/models/user.py
mindzie_api-2.0.0.dist-info/licenses/LICENSE
mindzie_api-2.0.0.dist-info/METADATA
mindzie_api-2.0.0.dist-info/WHEEL
mindzie_api-2.0.0.dist-info/top_level.txt
mindzie_api-2.0.0.dist-info/RECORD
