Metadata-Version: 2.4
Name: mindzie-api
Version: 2.0.0
Summary: Official Python client library for Mindzie Studio API
Home-page: https://github.com/mindzie/mindzie-api-python
Author: Mindzie
Author-email: Mindzie <support@mindzie.com>
Maintainer-email: Mindzie Development Team <dev@mindzie.com>
License: MIT
Project-URL: Homepage, https://github.com/mindzie/mindzie-api-python
Project-URL: Documentation, https://docs.mindzie.com/api/python
Project-URL: Repository, https://github.com/mindzie/mindzie-api-python
Project-URL: Issues, https://github.com/mindzie/mindzie-api-python/issues
Project-URL: Changelog, https://github.com/mindzie/mindzie-api-python/blob/main/CHANGELOG.md
Keywords: mindzie,api,client,studio,process mining,business intelligence,data analysis
Classifier: Development Status :: 5 - Production/Stable
Classifier: Intended Audience :: Developers
Classifier: Topic :: Software Development :: Libraries :: Python Modules
Classifier: License :: OSI Approved :: MIT License
Classifier: Operating System :: OS Independent
Classifier: Programming Language :: Python :: 3
Classifier: Programming Language :: Python :: 3.8
Classifier: Programming Language :: Python :: 3.9
Classifier: Programming Language :: Python :: 3.10
Classifier: Programming Language :: Python :: 3.11
Classifier: Programming Language :: Python :: 3.12
Classifier: Typing :: Typed
Requires-Python: >=3.8
License-File: LICENSE
Requires-Dist: requests>=2.28.0
Requires-Dist: python-dotenv>=1.0.0
Requires-Dist: pydantic>=2.0.0
Requires-Dist: typing-extensions>=4.0.0; python_version < "3.10"
Requires-Dist: urllib3>=1.26.0
Requires-Dist: certifi>=2022.0.0
Provides-Extra: dev
Requires-Dist: pytest>=7.0; extra == "dev"
Requires-Dist: pytest-cov>=4.0; extra == "dev"
Requires-Dist: pytest-asyncio>=0.21.0; extra == "dev"
Requires-Dist: pytest-mock>=3.10.0; extra == "dev"
Requires-Dist: responses>=0.23.0; extra == "dev"
Requires-Dist: faker>=18.0.0; extra == "dev"
Requires-Dist: black>=23.0; extra == "dev"
Requires-Dist: flake8>=6.0; extra == "dev"
Requires-Dist: mypy>=1.0; extra == "dev"
Requires-Dist: isort>=5.0; extra == "dev"
Requires-Dist: pre-commit>=3.0; extra == "dev"
Requires-Dist: tox>=4.0; extra == "dev"
Requires-Dist: sphinx>=6.0; extra == "dev"
Requires-Dist: sphinx-rtd-theme>=1.0; extra == "dev"
Requires-Dist: twine>=4.0; extra == "dev"
Requires-Dist: build>=0.10.0; extra == "dev"
Provides-Extra: async
Requires-Dist: aiohttp>=3.8.0; extra == "async"
Requires-Dist: aiofiles>=23.0; extra == "async"
Provides-Extra: azure
Requires-Dist: msal>=1.20.0; extra == "azure"
Requires-Dist: azure-identity>=1.12.0; extra == "azure"
Dynamic: author
Dynamic: home-page
Dynamic: license-file
Dynamic: requires-python
